GeoAPI/__init__.py
GeoAPI/cities.py
GeoAPI/countries.py
TranslatorAPI/__init__.py
TranslatorAPI/detector.py
TranslatorAPI/translator.py
Library_API-0.0.2.dist-info/METADATA
Library_API-0.0.2.dist-info/WHEEL
Library_API-0.0.2.dist-info/top_level.txt
Library_API-0.0.2.dist-info/RECORD
