Metadata-Version: 2.1
Name: Library-API
Version: 0.0.2
Summary: Sending request to API
Author: Tomasz Górniak
Author-email: <tgorniak_252697@e-science.pl>
Keywords: python,video,stream,video stream,camera stream,sockets
Classifier: Development Status :: 1 - Planning
Classifier: Intended Audience :: Developers
Classifier: Programming Language :: Python :: 3
Classifier: Operating System :: Unix
Classifier: Operating System :: MacOS :: MacOS X
Classifier: Operating System :: Microsoft :: Windows
Requires-Dist: requests
